zaqar_ui/__init__.py
zaqar_ui/karma.conf.js
zaqar_ui/version.py
zaqar_ui/api/__init__.py
zaqar_ui/api/zaqar.py
zaqar_ui/api/rest/__init__.py
zaqar_ui/api/rest/zaqar.py
zaqar_ui/content/__init__.py
zaqar_ui/content/pool_flavors/__init__.py
zaqar_ui/content/pool_flavors/panel.py
zaqar_ui/content/pool_flavors/urls.py
zaqar_ui/content/pools/__init__.py
zaqar_ui/content/pools/panel.py
zaqar_ui/content/pools/urls.py
zaqar_ui/content/queues/__init__.py
zaqar_ui/content/queues/panel.py
zaqar_ui/content/queues/urls.py
zaqar_ui/enabled/_1510_project_messaging_group.py
zaqar_ui/enabled/_1520_project_queues.py
zaqar_ui/enabled/_2510_admin_messaging_group.py
zaqar_ui/enabled/_2520_admin_pools.py
zaqar_ui/enabled/_2530_admin_pool_flavors.py
zaqar_ui/enabled/__init__.py
zaqar_ui/locale/de/LC_MESSAGES/django.po
zaqar_ui/locale/de/LC_MESSAGES/djangojs.po
zaqar_ui/locale/en_GB/LC_MESSAGES/django.po
zaqar_ui/locale/en_GB/LC_MESSAGES/djangojs.po
zaqar_ui/locale/fr/LC_MESSAGES/django.po
zaqar_ui/locale/id/LC_MESSAGES/django.po
zaqar_ui/locale/id/LC_MESSAGES/djangojs.po
zaqar_ui/locale/ja/LC_MESSAGES/django.po
zaqar_ui/locale/ja/LC_MESSAGES/djangojs.po
zaqar_ui/locale/ko_KR/LC_MESSAGES/django.po
zaqar_ui/locale/ko_KR/LC_MESSAGES/djangojs.po
zaqar_ui/locale/pt_BR/LC_MESSAGES/django.po
zaqar_ui/locale/pt_BR/LC_MESSAGES/djangojs.po
zaqar_ui/locale/ru/LC_MESSAGES/django.po
zaqar_ui/locale/ru/LC_MESSAGES/djangojs.po
zaqar_ui/locale/tr_TR/LC_MESSAGES/django.po
zaqar_ui/locale/tr_TR/LC_MESSAGES/djangojs.po
zaqar_ui/locale/zh_Hans/LC_MESSAGES/django.po
zaqar_ui/locale/zh_Hans/LC_MESSAGES/djangojs.po
zaqar_ui/static/app/core/openstack-service-api/zaqar.service.js
zaqar_ui/static/dashboard/admin/pool-flavors/drawer.html
zaqar_ui/static/dashboard/admin/pool-flavors/panel.html
zaqar_ui/static/dashboard/admin/pool-flavors/pool-flavors.module.js
zaqar_ui/static/dashboard/admin/pool-flavors/pool-flavors.scss
zaqar_ui/static/dashboard/admin/pool-flavors/pool-flavors.service.js
zaqar_ui-19.0.0.dist-info/AUTHORS
zaqar_ui-19.0.0.dist-info/LICENSE
zaqar_ui-19.0.0.dist-info/METADATA
zaqar_ui-19.0.0.dist-info/WHEEL
zaqar_ui-19.0.0.dist-info/pbr.json
zaqar_ui-19.0.0.dist-info/top_level.txt
zaqar_ui-19.0.0.dist-info/RECORD
